merpy/__init__.py
merpy/merpy.py
merpy/MER/NOTICE.txt
merpy/MER/README.md
merpy/MER/benchmark.py
merpy/MER/get_entities.sh
merpy/MER/produce_data_files.sh
merpy/MER/stopwords.txt
merpy/MER/test.sh
merpy/MER/data/lexicon.txt
merpy/MER/data/lexicon_links.tsv
merpy-1.7.13.dist-info/LICENSE
merpy-1.7.13.dist-info/METADATA
merpy-1.7.13.dist-info/WHEEL
merpy-1.7.13.dist-info/top_level.txt
merpy-1.7.13.dist-info/RECORD
