Metadata-Version: 2.1
Name: merpy
Version: 1.7.13
Summary: Use Minimal Named-Entity Recognizer (MER) inside python
Home-page: https://github.com/lasigeBioTM/merpy
Author: Andre Lamurias
Author-email: alamurias@lasige.di.fc.ul.pt
Maintainer: Francisco M Couto
Maintainer-email: fjcouto@ciencias.ulisboa.pt
License: UNKNOWN
Keywords: ner,named-entity recognition,entity linking,ontologies
Platform: UNKNOWN
Classifier: Programming Language :: Python :: 3
Classifier: License :: OSI Approved :: MIT License
Classifier: Operating System :: OS Independent
Provides-Extra: dev
Requires-Dist: setuptools-changelog ; extra == 'dev'
